{
  "students": [
    {
      "id": "2",
      "name": "Pradeep",
      "location": "US",
      "phone": "98876543213",
      "courses": [
        "Python",
        "Appium"
      ]
    },
    {
      "id": "3",
      "name": "Sivaram",
      "location": "Canada",
      "phone": "165498765",
      "courses": [
        "C#",
        "RestAPI"
      ]
    },
    {
      "id": 1,
      "name": "Krishna",
      "location": "india",
      "phone": "1234567890",
      "courses": [
        "Java",
        "Selenium"
      ]
    },
    {
      "id": "4c6c",
      "name": "Krishna",
      "location": "india",
      "phone": "1234567890",
      "courses": [
        "Java",
        "Selenium"
      ]
    }
  ]
}